jira_rabbitmq_webhook/__init__.py
jira_rabbitmq_webhook/amqp.py
jira_rabbitmq_webhook/application.py
jira_rabbitmq_webhook/config.py
jira_rabbitmq_webhook/errors.py
jira_rabbitmq_webhook-0.1.3.data/data/config/jira_rabbitmq_webhook.json.example
jira_rabbitmq_webhook-0.1.3.dist-info/LICENSE
jira_rabbitmq_webhook-0.1.3.dist-info/METADATA
jira_rabbitmq_webhook-0.1.3.dist-info/WHEEL
jira_rabbitmq_webhook-0.1.3.dist-info/top_level.txt
jira_rabbitmq_webhook-0.1.3.dist-info/RECORD
