Metadata-Version: 2.1
Name: jira-rabbitmq-webhook
Version: 0.1.3
Summary: A microservice for retranslating Jira webhooks to a RabbitMQ server
Home-page: https://github.com/GrayAn/jira_rabbitmq_webhook
Author: Sergey Shubin
Author-email: greyan@gmail.com
License: MIT
Platform: UNKNOWN
Classifier: Development Status :: 5 - Production/Stable
Classifier: Framework :: AsyncIO
Classifier: Intended Audience :: Developers
Classifier: Intended Audience :: Information Technology
Classifier: Intended Audience :: System Administrators
Classifier: License :: OSI Approved :: MIT License
Classifier: Operating System :: MacOS
Classifier: Operating System :: POSIX
Classifier: Programming Language :: Python :: 3.5
Classifier: Programming Language :: Python :: 3.6
Classifier: Programming Language :: Python :: 3.7
Classifier: Programming Language :: Python :: 3.8
Classifier: Programming Language :: Python :: 3.9
Classifier: Topic :: Software Development :: Bug Tracking
Requires-Python: >=3.5
License-File: LICENSE
Requires-Dist: aioamqp (<1.0)
Requires-Dist: aiohttp (<4.0,>=3.0)
